Metadata-Version: 2.4
Name: mpi4jax
Version: 0.8.1.post2
Summary: Zero-copy MPI communication of JAX arrays, for turbo-charged HPC applications in Python ⚡
Home-page: https://github.com/mpi4jax/mpi4jax
Author: Filippo Vicentini
Author-email: filippovicentini@gmail.com
License: MIT
Classifier: Programming Language :: Python :: 3
Classifier: Programming Language :: Cython
Classifier: Development Status :: 3 - Alpha
Classifier: Environment :: GPU :: NVIDIA CUDA
Classifier: Intended Audience :: Science/Research
Classifier: License :: OSI Approved :: MIT License
Classifier: Operating System :: MacOS :: MacOS X
Classifier: Operating System :: POSIX :: Linux
Classifier: Operating System :: Unix
Classifier: Topic :: Scientific/Engineering
Requires-Python: >=3.10
License-File: LICENSE.md
Requires-Dist: mpi4py>=3.0.1
Requires-Dist: numpy
Requires-Dist: jax>=0.5.1
Provides-Extra: dev
Requires-Dist: pytest>=6; extra == "dev"
Requires-Dist: pytest-cov>=2.10.1; extra == "dev"
Requires-Dist: coverage[toml]>=5; extra == "dev"
Requires-Dist: pre-commit; extra == "dev"
Requires-Dist: black==23.9; python_version >= "3.8.0" and extra == "dev"
Requires-Dist: flake8==3.9.2; extra == "dev"
Requires-Dist: tqdm>=4.52; extra == "dev"
Dynamic: author
Dynamic: author-email
Dynamic: classifier
Dynamic: description
Dynamic: home-page
Dynamic: license
Dynamic: license-file
Dynamic: provides-extra
Dynamic: requires-dist
Dynamic: requires-python
Dynamic: summary
